{
  "id": "1488500707635105923",
  "name": "1wt 1x locked input box unloader",
  "code": "BU012",
  "reservedCodes": [
    "BU012"
  ],
  "pastPostThreadIds": [
    "1488589355634262147"
  ],
  "authors": [
    {
      "type": "discord-in-guild",
      "id": "688456529338433611",
      "username": "glidingmonkey",
      "displayName": "Christone",
      "iconURL": "https://cdn.discordapp.com/avatars/688456529338433611/348a34add443a5a71237111010e484b1.webp"
    },
    {
      "type": "discord-in-guild",
      "id": "660633169191632908",
      "username": "etikle",
      "displayName": "Passionate Storage Techer 69",
      "iconURL": "https://cdn.discordapp.com/avatars/660633169191632908/552443236bae5d574b5b1aec2694b58f.webp"
    },
    {
      "type": "discord-in-guild",
      "id": "381396930212921355",
      "username": "commandleo",
      "displayName": "CommandLeo",
      "iconURL": "https://cdn.discordapp.com/avatars/381396930212921355/cb1dcc76d3f6a30dddc49e6d9e96681a.webp"
    }
  ],
  "endorsers": [
    {
      "type": "discord-in-guild",
      "id": "239078039831445504",
      "username": "andrews54757",
      "displayName": "Andrews54757",
      "iconURL": "https://cdn.discordapp.com/avatars/239078039831445504/3cabc63679bd9d8d74073833458570b3.webp"
    }
  ],
  "tags": [
    {
      "id": "1465490889140076728",
      "name": "Functional"
    },
    {
      "id": "1465487154460364877",
      "name": "Recommended"
    },
    {
      "id": "1465521347378675817",
      "name": "Independently Tested"
    },
    {
      "id": "1386248557111017532",
      "name": "1X Hopperspeed"
    }
  ],
  "images": [
    {
      "id": "1488562949223219260",
      "name": "image.png",
      "contentType": "image/png",
      "url": "https://cdn.discordapp.com/attachments/1488500707635105923/1488562949223219260/image.png?ex=69cd3bc7&is=69cbea47&hm=3075bd880edb7c3c86ff3f594e29db069517a7722f4283e0573c81c8b71d01b3&",
      "timestamp": 1774971463296,
      "author": {
        "type": "discord-in-guild",
        "id": "239078039831445504",
        "username": "andrews54757",
        "displayName": "Andrews54757",
        "iconURL": "https://cdn.discordapp.com/avatars/239078039831445504/3cabc63679bd9d8d74073833458570b3.webp"
      },
      "source": "MessageAttachment",
      "description": "",
      "size": 14614,
      "canDownload": true,
      "width": 844,
      "height": 970,
      "path": "images/image.png",
      "hash": "8b8317de7bb2d607c96530705d9c8213cea13a2e65806edc77552b97a523d2e7"
    }
  ],
  "attachments": [
    {
      "id": "1488563603081658670",
      "name": "BU012_1wt_1x_locked_input_box_unloader.litematic",
      "contentType": "unknown",
      "url": "https://cdn.discordapp.com/attachments/1488500707635105923/1488563603081658670/1wt_1x_Box_Unloader.litematic?ex=69cd3c63&is=69cbeae3&hm=db8480c78d02c25999350f40f61c5a1775e3f7fcb53afb2b381752df202473a8&",
      "timestamp": 1774971619231,
      "author": {
        "type": "discord-in-guild",
        "id": "239078039831445504",
        "username": "andrews54757",
        "displayName": "Andrews54757",
        "iconURL": "https://cdn.discordapp.com/avatars/239078039831445504/3cabc63679bd9d8d74073833458570b3.webp"
      },
      "source": "MessageAttachment",
      "description": "",
      "size": 16708,
      "canDownload": true,
      "hash": "44bc221ac9dc20e8f46d07a3e2d609d583e779752533620db065ec0fb19dbc8c",
      "path": "attachments/BU012_1wt_1x_locked_input_box_unloader.litematic",
      "litematic": {
        "size": "1x8x7",
        "version": "1.14"
      }
    }
  ],
  "records": {
    "description": "Bufferless 1wABt 1x Box Unloader",
    "features": [
      "Unloads shulker boxes at 1x hopper speed.",
      "1-wide tileable. 7x8.",
      "First box detection.",
      "Handles empty boxes.",
      "No buffered items in the output.",
      "Max of 2 boxes buffered in input"
    ],
    "considerations": [
      "Empty box collection has to be global."
    ],
    "notes": "Compared to BU010, this unloader buffers less boxes in the input and has global box output",
    "compatibility": "[1.14+]"
  },
  "styles": {},
  "references": [
    {
      "type": "dictionaryTerm",
      "term": "A/B Tiling",
      "id": "1454753732293033984",
      "url": "https://discord.com/channels/1375556143186837695/1454753732293033984/1454753733035687988",
      "matches": [
        "1wABt"
      ]
    },
    {
      "type": "dictionaryTerm",
      "term": "Hopper speed",
      "id": "1454937395693879409",
      "url": "https://discord.com/channels/1375556143186837695/1454937395693879409/1454937397304365294",
      "matches": [
        "1x",
        "hopper speed"
      ]
    },
    {
      "type": "dictionaryTerm",
      "term": "Unloader",
      "id": "1454754824758493380",
      "url": "https://discord.com/channels/1375556143186837695/1454754824758493380/1454754825345433803",
      "matches": [
        "Unloader",
        "unloader"
      ]
    },
    {
      "type": "dictionaryTerm",
      "term": "Box Detection",
      "id": "1454753490936266762",
      "url": "https://discord.com/channels/1375556143186837695/1454753490936266762/1454753491787452438",
      "matches": [
        "box detection"
      ]
    },
    {
      "type": "dictionaryTerm",
      "term": "Box Collection",
      "id": "1454805930670559326",
      "url": "https://discord.com/channels/1375556143186837695/1454805930670559326/1454805932532830268",
      "matches": [
        "box collection"
      ]
    },
    {
      "type": "dictionaryTerm",
      "term": "Global",
      "id": "1454753648574992557",
      "url": "https://discord.com/channels/1375556143186837695/1454753648574992557/1454753649480958066",
      "matches": [
        "global"
      ]
    },
    {
      "type": "archivedPost",
      "id": "1399539219826999418",
      "code": "BU010",
      "name": "1wt Full-Featured Box Unloader",
      "url": "https://discord.com/channels/1375556143186837695/1401249609904554225",
      "path": "Archive/BU_box-unloaders/BU010_1wt_Full-Featured_Box_Unloader",
      "matches": [
        "BU010"
      ]
    }
  ],
  "author_references": [],
  "post": {
    "threadId": "1488589355634262147",
    "forumId": "1375560446676963450",
    "continuingMessageIds": [
      "1488589363989446687"
    ],
    "threadURL": "https://discord.com/channels/1375556143186837695/1488589355634262147",
    "uploadMessageId": "1488589353344040971",
    "thumbnailURL": "https://cdn.discordapp.com/attachments/1488589355634262147/1488589359757131797/image.png?ex=69cd5460&is=69cc02e0&hm=d626281544b9e251d5e60e04bc3d8922241fd638f515b5260cfccb0db836487d&"
  },
  "archivedAt": 1774977751201,
  "updatedAt": 1774977893273,
  "num_comments": 0
}